wpilib/__init__.py
wpilib/cameraserver.py
wpilib/deployinfo.py
wpilib/py.typed
wpilib/version.py
wpilib/_impl/__init__.py
wpilib/_impl/main.py
wpilib/_impl/report_error.py
wpilib/_impl/start.py
wpilib/_impl/utils.py
wpilib/counter/__init__.py
wpilib/counter/counter.cpp
wpilib/drive/__init__.py
wpilib/drive/drive.cpp
wpilib/event/__init__.py
wpilib/event/event.cpp
wpilib/interfaces/__init__.py
wpilib/interfaces/interfaces.cpp
wpilib/shuffleboard/ShuffleboardData.cpp
wpilib/shuffleboard/ShuffleboardData.h
wpilib/shuffleboard/__init__.py
wpilib/shuffleboard/shuffleboard.cpp
wpilib/simulation/__init__.py
wpilib/simulation/simulation.cpp
wpilib/src/main.cpp
wpilib/src/rpy/ControlWord.cpp
wpilib/src/rpy/ControlWord.h
wpilib/src/rpy/Filesystem.h
wpilib/src/rpy/Filesystem.inc
wpilib/src/rpy/MotorControllerGroup.cpp
wpilib/src/rpy/MotorControllerGroup.h
wpilib/src/rpy/Notifier.cpp
wpilib/src/rpy/Notifier.h
wpilib/src/rpy/SmartDashboardData.cpp
wpilib/src/rpy/SmartDashboardData.h
wpilib/sysid/__init__.py
wpilib/_init__wpilib.py
wpilib/_wpilib.cp311-win_amd64.lib
wpilib/_wpilib.cp311-win_amd64.pyd
wpilib/wpilib.pc
wpilib/_wpilib/__init__.pyi
wpilib/_wpilib/sysid.pyi
wpilib/counter/_counter.cp311-win_amd64.lib
wpilib/counter/_counter.cp311-win_amd64.pyd
wpilib/counter/_counter.pyi
wpilib/counter/_init__counter.py
wpilib/counter/wpilib_counter.pc
wpilib/drive/_drive.cp311-win_amd64.lib
wpilib/drive/_drive.cp311-win_amd64.pyd
wpilib/drive/_drive.pyi
wpilib/drive/_init__drive.py
wpilib/drive/wpilib_drive.pc
wpilib/event/_event.cp311-win_amd64.lib
wpilib/event/_event.cp311-win_amd64.pyd
wpilib/event/_event.pyi
wpilib/event/_init__event.py
wpilib/event/wpilib_event.pc
wpilib/interfaces/_init__interfaces.py
wpilib/interfaces/_interfaces.cp311-win_amd64.lib
wpilib/interfaces/_interfaces.cp311-win_amd64.pyd
wpilib/interfaces/_interfaces.pyi
wpilib/interfaces/wpilib_interfaces.pc
wpilib/shuffleboard/_init__shuffleboard.py
wpilib/shuffleboard/_shuffleboard.cp311-win_amd64.lib
wpilib-2025.3.2.3.dist-info/METADATA
wpilib-2025.3.2.3.dist-info/WHEEL
wpilib-2025.3.2.3.dist-info/entry_points.txt
wpilib-2025.3.2.3.dist-info/licenses/LICENSE.txt
wpilib-2025.3.2.3.dist-info/RECORD
