Metadata-Version: 2.4
Name: wpilib
Version: 2025.3.2.3
Summary: Binary wrapper for FRC WPILib
Project-URL: Source code, https://github.com/robotpy/mostrobotpy
Author-email: RobotPy Development Team <robotpy@googlegroups.com>
License-Expression: BSD-3-Clause
License-File: LICENSE.txt
Requires-Dist: pyntcore==2025.3.2.3
Requires-Dist: robotpy-cli~=2024.0b
Requires-Dist: robotpy-hal==2025.3.2.3
Requires-Dist: robotpy-native-wpilib==2025.3.2
Requires-Dist: robotpy-wpimath==2025.3.2.3
Requires-Dist: robotpy-wpiutil==2025.3.2.3
